gump/__init__.py
gump/algorithm.py
gump/app.py
gump/applogger.py
gump/batch.py
gump/parser.py
gump/test.py
gump/utils.py
gump-0.0.3.dist-info/licenses/LICENSE
gump-0.0.3.dist-info/METADATA
gump-0.0.3.dist-info/WHEEL
gump-0.0.3.dist-info/entry_points.txt
gump-0.0.3.dist-info/top_level.txt
gump-0.0.3.dist-info/RECORD
